intelisys/__init__.py
intelisys/intelisys copy.py
intelisys/intelisys.py
intelisys-0.5.6.dist-info/LICENSE
intelisys-0.5.6.dist-info/METADATA
intelisys-0.5.6.dist-info/WHEEL
intelisys-0.5.6.dist-info/top_level.txt
intelisys-0.5.6.dist-info/RECORD
