Metadata-Version: 2.1
Name: intelisys
Version: 0.5.6
Summary: Intelligence/AI services for the Lifsys Enterprise with enhanced max_history_words, efficient history trimming, and improved document processing
Home-page: https://github.com/lifsys/intelisys
Author: Lifsys Enterprise
Author-email: Lifsys Enterprise <contact@lifsys.com>
License: MIT License
Project-URL: Homepage, https://github.com/lifsys/intelisys
Project-URL: Documentation, https://intelisys.readthedocs.io/
Project-URL: Repository, https://github.com/lifsys/intelisys.git
Project-URL: Bug Tracker, https://github.com/lifsys/intelisys/issues
Keywords: ai,intelligence,openai,anthropic,google,groq,openrouter,document processing
Classifier: Development Status :: 4 - Beta
Classifier: Intended Audience :: Developers
Classifier: License :: OSI Approved :: MIT License
Classifier: Operating System :: OS Independent
Classifier: Programming Language :: Python :: 3
Classifier: Programming Language :: Python :: 3.7
Classifier: Programming Language :: Python :: 3.8
Classifier: Programming Language :: Python :: 3.9
Classifier: Programming Language :: Python :: 3.10
Classifier: Programming Language :: Python :: 3.11
Requires-Python: >=3.7
License-File: LICENSE
Requires-Dist: openai>=1.0.0
Requires-Dist: jinja2>=3.0.0
Requires-Dist: onepasswordconnectsdk>=1.0.0
Requires-Dist: anthropic>=0.3.0
Requires-Dist: pillow>=8.0.0
Requires-Dist: termcolor>=1.1.0
Requires-Dist: aiohttp>=3.7.4
Requires-Dist: pydantic>=1.8.0
Requires-Dist: PyPDF2>=1.26.0
Requires-Dist: python-pptx>=0.6.18
Requires-Dist: openpyxl>=3.0.7
Requires-Dist: python-docx>=0.8.11
Requires-Dist: chardet>=4.0.0
Provides-Extra: dev
Requires-Dist: pytest>=6.0; extra == "dev"
Requires-Dist: pytest-cov>=2.0; extra == "dev"
Requires-Dist: flake8>=3.9; extra == "dev"
Requires-Dist: black>=21.5b1; extra == "dev"
